neutpy/__init__.py
neutpy/UnitTest/TestSuite.py
neutpy/UnitTest/__init__.py
neutpy/crosssections/__init__.py
neutpy/crosssections/crosssections.py
neutpy/parallelNeut/__init__.py
neutpy/parallelNeut/parallelNeut.py
neutpy/physics/__init__.py
neutpy/physics/physics.py
neutpy/plot/__init__.py
neutpy/plot/plot.py
neutpy/tools/__init__.py
neutpy/tools/tools.py
neutpy-0.0.3.dist-info/LICENSE
neutpy-0.0.3.dist-info/METADATA
neutpy-0.0.3.dist-info/WHEEL
neutpy-0.0.3.dist-info/top_level.txt
neutpy-0.0.3.dist-info/RECORD
