Metadata-Version: 2.1
Name: neutpy
Version: 0.0.3
Summary: NeutPy - A neutrals code for tokamak fusion reactors
Home-page: https://github.com/gt-frc/neutpy/
Author: Maxwell D. Hill, Jonathan J. Roveto
Author-email: max.hill@pm.me, veto1024@gmail.com
License: UNKNOWN
Platform: UNKNOWN
Classifier: Programming Language :: Python :: 2.7
Classifier: License :: OSI Approved :: MIT License
Classifier: Operating System :: OS Independent
Classifier: Development Status :: 4 - Beta
Classifier: Intended Audience :: Science/Research
Classifier: Natural Language :: English
Classifier: Topic :: Scientific/Engineering :: Physics
Requires-Python: >=2.7
Requires-Dist: PyYAML
Requires-Dist: Shapely
Requires-Dist: matplotlib
Requires-Dist: multiprocess
Requires-Dist: numpy
Requires-Dist: pandas
Requires-Dist: pathos
Requires-Dist: scipy
